semantic_tree/__init__.py
semantic_tree/semtree.py
semantic_tree-1.1.1.dist-info/entry_points.txt
semantic_tree-1.1.1.dist-info/LICENSE.txt
semantic_tree-1.1.1.dist-info/WHEEL
semantic_tree-1.1.1.dist-info/METADATA
semantic_tree-1.1.1.dist-info/RECORD
