Metadata-Version: 2.1
Name: semantic-tree
Version: 1.1.1
Summary: Creates a visualization of the semantic neighborhood of a word in a Gensim's Word2Vec vector space model using the Gource visualizer
Home-page: https://github.com/fccoelho/SemanticTree
License: MIT
Author: Flávio Codeço Coelho
Author-email: fccoelho@gmail.com
Requires-Python: >=3.10,<4.0
Classifier: License :: OSI Approved :: MIT License
Classifier: Programming Language :: Python :: 3
Classifier: Programming Language :: Python :: 3.10
Classifier: Programming Language :: Python :: 3.11
Requires-Dist: gensim (>=4.2.0,<5.0.0)
Requires-Dist: matplotlib (>=3.6.2,<4.0.0)
Requires-Dist: networkx (>=2.8.8,<3.0.0)
Project-URL: Changelog, https://github.com/fccoelho/SemanticTree/releases
Project-URL: Repository, https://github.com/fccoelho/SemanticTree
